workday/__init__.py
workday/auth.py
workday/client.py
workday/exceptions.py
workday/soap.py
workday-0.4.0.dist-info/METADATA
workday-0.4.0.dist-info/RECORD
workday-0.4.0.dist-info/WHEEL
workday-0.4.0.dist-info/top_level.txt
