Metadata-Version: 2.1
Name: workday
Version: 0.4.0
Summary: Python client for Workday tenants
Home-page: https://github.com/tonybaloney/workday
Author: Anthony Shaw
Author-email: anthonyshaw@apache.org
License: Apache License (2.0)
Keywords: workday
Platform: UNKNOWN
Classifier: Development Status :: 5 - Production/Stable
Classifier: Environment :: Console
Classifier: Intended Audience :: Developers
Classifier: Intended Audience :: System Administrators
Classifier: License :: OSI Approved :: Apache Software License
Classifier: Operating System :: OS Independent
Classifier: Programming Language :: Python
Classifier: Topic :: Software Development :: Libraries :: Python Modules
Classifier: Programming Language :: Python :: 2.7
Classifier: Programming Language :: Python :: 3
Classifier: Programming Language :: Python :: 3.3
Classifier: Programming Language :: Python :: 3.4
Classifier: Programming Language :: Python :: 3.5
Classifier: Programming Language :: Python :: 3.6
Classifier: Programming Language :: Python :: Implementation :: CPython
Classifier: Programming Language :: Python :: Implementation :: PyPy
Requires-Dist: zeep (<4.0.0,>=3.0.0)
Requires-Dist: requests
Requires-Dist: six
